__init__.py
makeMoney.py
makeMoney-2.1.dist-info/LICENSE
makeMoney-2.1.dist-info/METADATA
makeMoney-2.1.dist-info/WHEEL
makeMoney-2.1.dist-info/top_level.txt
makeMoney-2.1.dist-info/RECORD
