Metadata-Version: 2.1
Name: makeMoney
Version: 2.1
Summary: we report a computational method and program（makeMoney）based on the Python programming language for basic data analysis and processing in Convertible bonds.
Author-email: Guixian Yang <Ygxyoung@hotmail.com>
Project-URL: Homepage, https://github.com/
Project-URL: Bug Tracker, https://github.com
Classifier: Programming Language :: Python :: 3
Classifier: License :: OSI Approved :: MIT License
Requires-Python: >=3.7
License-File: LICENSE
